streamlit_rich_message_history/__init__.py
streamlit_rich_message_history/components.py
streamlit_rich_message_history/enums.py
streamlit_rich_message_history/history.py
streamlit_rich_message_history/messages.py
streamlit_rich_message_history/utils.py
streamlit_rich_message_history-0.1.6.dist-info/LICENSE
streamlit_rich_message_history-0.1.6.dist-info/METADATA
streamlit_rich_message_history-0.1.6.dist-info/WHEEL
streamlit_rich_message_history-0.1.6.dist-info/RECORD
