Metadata-Version: 2.3
Name: streamlit-rich-message-history
Version: 0.1.6
Summary: A package for creating rich, multi-component chat messages in Streamlit.
License: MIT
Keywords: streamlit,chat,messages,rich,ui
Author: Ethan Christensen
Author-email: ethanlchristensen@outlook.com
Requires-Python: >=3.11,<3.14
Classifier: Development Status :: 4 - Beta
Classifier: Intended Audience :: Developers
Classifier: License :: OSI Approved :: MIT License
Classifier: Programming Language :: Python :: 3
Classifier: Programming Language :: Python :: 3.11
Classifier: Programming Language :: Python :: 3.12
Classifier: Programming Language :: Python :: 3.13
Classifier: Topic :: Software Development :: Libraries :: Python Modules
Requires-Dist: matplotlib (>=3.10.1,<4.0.0)
Requires-Dist: pandas (>=2.2.3,<3.0.0)
Requires-Dist: plotly (>=6.0.0,<7.0.0)
Requires-Dist: streamlit (>=1.43.2,<2.0.0)
Project-URL: Repository, https://github.com/ethanlchristensen/streamlit-rich-message-history
